{
  "FIDES Example Provider:cred:eu:lpid:vcdm-2-0": {
    "firstSeenAt": "2026-03-12T00:00:00.000Z",
    "lastSeenAt": "2026-03-12T10:03:20.641Z"
  },
  "FIDES Community:cred:fides:lpid:sd-jwt-vc": {
    "firstSeenAt": "2026-03-12T00:00:00.000Z",
    "lastSeenAt": "2026-03-23T07:20:14.767Z"
  },
  "FIDES Community:cred:fides:bri:sd-jwt-vc": {
    "firstSeenAt": "2026-03-12T00:00:00.000Z",
    "lastSeenAt": "2026-03-23T07:20:14.767Z"
  },
  "FIDES Community:cred:fides:brp:sd-jwt-vc": {
    "firstSeenAt": "2026-03-12T00:00:00.000Z",
    "lastSeenAt": "2026-03-23T07:20:14.767Z"
  },
  "FIDES Community:cred:fides:company-roles:sd-jwt-vc": {
    "firstSeenAt": "2026-03-12T00:00:00.000Z",
    "lastSeenAt": "2026-03-23T07:20:14.767Z"
  },
  "FIDES Community:cred:fides:contact-details:sd-jwt-vc": {
    "firstSeenAt": "2026-03-12T00:00:00.000Z",
    "lastSeenAt": "2026-03-23T07:20:14.767Z"
  },
  "FIDES Community:cred:fides:einvoicing:sd-jwt-vc": {
    "firstSeenAt": "2026-03-12T00:00:00.000Z",
    "lastSeenAt": "2026-03-23T07:20:14.767Z"
  },
  "FIDES Community:cred:fides:green-lane:sd-jwt-vc": {
    "firstSeenAt": "2026-03-12T00:00:00.000Z",
    "lastSeenAt": "2026-03-23T07:20:14.767Z"
  },
  "FIDES Community:cred:fides:iban:sd-jwt-vc": {
    "firstSeenAt": "2026-03-12T00:00:00.000Z",
    "lastSeenAt": "2026-03-23T07:20:14.767Z"
  },
  "FIDES Community:cred:fides:iscc-sd:sd-jwt-vc": {
    "firstSeenAt": "2026-03-12T00:00:00.000Z",
    "lastSeenAt": "2026-03-23T07:20:14.767Z"
  },
  "FIDES Community:cred:fides:iscc-cert:sd-jwt-vc": {
    "firstSeenAt": "2026-03-12T00:00:00.000Z",
    "lastSeenAt": "2026-03-23T07:20:14.767Z"
  },
  "FIDES Community:cred:fides:iscc-role:sd-jwt-vc": {
    "firstSeenAt": "2026-03-12T00:00:00.000Z",
    "lastSeenAt": "2026-03-23T07:20:14.767Z"
  },
  "FIDES Community:cred:fides:iscc-cb:sd-jwt-vc": {
    "firstSeenAt": "2026-03-12T00:00:00.000Z",
    "lastSeenAt": "2026-03-23T07:20:14.767Z"
  },
  "FIDES Community:cred:fides:iscc-rev-user:sd-jwt-vc": {
    "firstSeenAt": "2026-03-12T00:00:00.000Z",
    "lastSeenAt": "2026-03-23T07:20:14.767Z"
  },
  "FIDES Community:cred:fides:notary-incorporation:sd-jwt-vc": {
    "firstSeenAt": "2026-03-12T00:00:00.000Z",
    "lastSeenAt": "2026-03-23T07:20:14.767Z"
  },
  "FIDES Community:cred:fides:pid:sd-jwt-vc": {
    "firstSeenAt": "2026-03-12T00:00:00.000Z",
    "lastSeenAt": "2026-03-23T07:20:14.767Z"
  },
  "FIDES Community:cred:fides:vat:sd-jwt-vc": {
    "firstSeenAt": "2026-03-12T00:00:00.000Z",
    "lastSeenAt": "2026-03-23T07:20:14.767Z"
  },
  "European Commission:cred:eu:diploma-vc-sd-jwt:sd-jwt-vc": {
    "firstSeenAt": "2026-03-17T09:29:34.000Z",
    "lastSeenAt": "2026-03-23T07:20:14.767Z"
  },
  "European Commission:cred:eu:ehic-sd-jwt-vc:sd-jwt-vc": {
    "firstSeenAt": "2026-03-17T09:29:34.000Z",
    "lastSeenAt": "2026-03-23T07:20:14.767Z"
  },
  "European Commission:cred:eu:hiid-sd-jwt-vc:sd-jwt-vc": {
    "firstSeenAt": "2026-03-17T09:29:34.000Z",
    "lastSeenAt": "2026-03-23T07:20:14.767Z"
  },
  "European Commission:cred:eu:iban-sd-jwt-vc:sd-jwt-vc": {
    "firstSeenAt": "2026-03-17T09:29:34.000Z",
    "lastSeenAt": "2026-03-23T07:20:14.767Z"
  },
  "European Commission:cred:eu:msisdn-sd-jwt-vc:sd-jwt-vc": {
    "firstSeenAt": "2026-03-17T09:29:34.000Z",
    "lastSeenAt": "2026-03-23T07:20:14.767Z"
  },
  "European Commission:cred:eu:pda1-sd-jwt-vc:sd-jwt-vc": {
    "firstSeenAt": "2026-03-17T09:29:34.000Z",
    "lastSeenAt": "2026-03-23T07:20:14.767Z"
  },
  "European Commission:cred:eu:pid-vc-sd-jwt:sd-jwt-vc": {
    "firstSeenAt": "2026-03-17T09:29:34.000Z",
    "lastSeenAt": "2026-03-23T07:20:14.767Z"
  },
  "European Commission:cred:eu:por-sd-jwt-vc:sd-jwt-vc": {
    "firstSeenAt": "2026-03-17T09:29:34.000Z",
    "lastSeenAt": "2026-03-23T07:20:14.767Z"
  },
  "European Commission:cred:eu:tax-residency-vc-sd-jwt:sd-jwt-vc": {
    "firstSeenAt": "2026-03-17T09:29:34.000Z",
    "lastSeenAt": "2026-03-23T07:20:14.767Z"
  },
  "European Commission:cred:eu:tax-sd-jwt-vc:sd-jwt-vc": {
    "firstSeenAt": "2026-03-17T09:29:34.000Z",
    "lastSeenAt": "2026-03-23T07:20:14.767Z"
  },
  "European Commission:cred:eu:cor-mdoc:mdoc": {
    "firstSeenAt": "2026-03-17T09:29:34.000Z",
    "lastSeenAt": "2026-03-23T07:20:14.767Z"
  },
  "European Commission:cred:eu:ehic-mdoc:mdoc": {
    "firstSeenAt": "2026-03-17T09:29:34.000Z",
    "lastSeenAt": "2026-03-23T07:20:14.767Z"
  },
  "European Commission:cred:eu:employee-mdoc:mdoc": {
    "firstSeenAt": "2026-03-17T09:29:34.000Z",
    "lastSeenAt": "2026-03-23T07:20:14.767Z"
  },
  "European Commission:cred:eu:hiid-mdoc:mdoc": {
    "firstSeenAt": "2026-03-17T09:29:34.000Z",
    "lastSeenAt": "2026-03-23T07:20:14.767Z"
  },
  "European Commission:cred:eu:iban-mdoc:mdoc": {
    "firstSeenAt": "2026-03-17T09:29:34.000Z",
    "lastSeenAt": "2026-03-23T07:20:14.767Z"
  },
  "European Commission:cred:eu:loyalty-mdoc:mdoc": {
    "firstSeenAt": "2026-03-17T09:29:34.000Z",
    "lastSeenAt": "2026-03-23T07:20:14.767Z"
  },
  "European Commission:cred:eu:mdl-mdoc:mdoc": {
    "firstSeenAt": "2026-03-17T09:29:34.000Z",
    "lastSeenAt": "2026-03-23T07:20:14.767Z"
  },
  "European Commission:cred:eu:msisdn-mdoc:mdoc": {
    "firstSeenAt": "2026-03-17T09:29:34.000Z",
    "lastSeenAt": "2026-03-23T07:20:14.767Z"
  },
  "European Commission:cred:eu:pda1-mdoc:mdoc": {
    "firstSeenAt": "2026-03-17T09:29:34.000Z",
    "lastSeenAt": "2026-03-23T07:20:14.767Z"
  },
  "European Commission:cred:eu:photoid-mdoc:mdoc": {
    "firstSeenAt": "2026-03-17T09:29:34.000Z",
    "lastSeenAt": "2026-03-23T07:20:14.767Z"
  },
  "European Commission:cred:eu:pid-mdoc:mdoc": {
    "firstSeenAt": "2026-03-17T09:29:34.000Z",
    "lastSeenAt": "2026-03-23T07:20:14.767Z"
  },
  "European Commission:cred:eu:pid-mdoc-deferred-mdoc:mdoc": {
    "firstSeenAt": "2026-03-17T09:29:34.000Z",
    "lastSeenAt": "2026-03-23T07:20:14.767Z"
  },
  "European Commission:cred:eu:por-mdoc:mdoc": {
    "firstSeenAt": "2026-03-17T09:29:34.000Z",
    "lastSeenAt": "2026-03-23T07:20:14.767Z"
  },
  "European Commission:cred:eu:seafarer-mdoc:mdoc": {
    "firstSeenAt": "2026-03-17T09:29:34.000Z",
    "lastSeenAt": "2026-03-23T07:20:14.767Z"
  },
  "European Commission:cred:eu:tax-mdoc:mdoc": {
    "firstSeenAt": "2026-03-17T09:29:34.000Z",
    "lastSeenAt": "2026-03-23T07:20:14.767Z"
  },
  "European Commission:cred:eu:reservation-mdoc:mdoc": {
    "firstSeenAt": "2026-03-17T09:29:34.000Z",
    "lastSeenAt": "2026-03-23T07:20:14.767Z"
  },
  "University of the Aegean / EWC:cred:ewc:pda1-sd-jwt:sd-jwt-vc": {
    "firstSeenAt": "2026-03-17T16:20:30.000Z",
    "lastSeenAt": "2026-03-23T07:20:14.767Z"
  },
  "University of the Aegean / EWC:cred:ewc:pda2-sd-jwt:sd-jwt-vc": {
    "firstSeenAt": "2026-03-17T16:20:30.000Z",
    "lastSeenAt": "2026-03-23T07:20:14.767Z"
  },
  "University of the Aegean / EWC:cred:ewc:id-card-jwt-vc:jwt-vc": {
    "firstSeenAt": "2026-03-17T16:20:30.000Z",
    "lastSeenAt": "2026-03-23T07:20:14.767Z"
  },
  "University of the Aegean / EWC:cred:ewc:pid-sd-jwt:sd-jwt-vc": {
    "firstSeenAt": "2026-03-17T16:20:30.000Z",
    "lastSeenAt": "2026-03-23T07:20:14.767Z"
  },
  "University of the Aegean / EWC:cred:ewc:epassport-sd-jwt:sd-jwt-vc": {
    "firstSeenAt": "2026-03-17T16:20:30.000Z",
    "lastSeenAt": "2026-03-23T07:20:14.767Z"
  },
  "University of the Aegean / EWC:cred:ewc:student-id-sd-jwt:sd-jwt-vc": {
    "firstSeenAt": "2026-03-17T16:20:30.000Z",
    "lastSeenAt": "2026-03-23T07:20:14.767Z"
  },
  "University of the Aegean / EWC:cred:ewc:ferry-boarding-pass-sd-jwt:sd-jwt-vc": {
    "firstSeenAt": "2026-03-17T16:20:30.000Z",
    "lastSeenAt": "2026-03-23T07:20:14.767Z"
  },
  "University of the Aegean / EWC:cred:ewc:vreceipt-sd-jwt:sd-jwt-vc": {
    "firstSeenAt": "2026-03-17T16:20:30.000Z",
    "lastSeenAt": "2026-03-23T07:20:14.767Z"
  },
  "University of the Aegean / EWC:cred:ewc:pid-eudi-sd-jwt:sd-jwt-vc": {
    "firstSeenAt": "2026-03-17T16:20:30.000Z",
    "lastSeenAt": "2026-03-23T07:20:14.767Z"
  },
  "University of the Aegean / EWC:cred:ewc:pid-eudi-mdoc:mso-mdoc": {
    "firstSeenAt": "2026-03-17T16:20:30.000Z",
    "lastSeenAt": "2026-03-23T07:20:14.767Z"
  },
  "University of the Aegean / EWC:cred:ewc:payment-wallet-attestation-sd-jwt:sd-jwt-vc": {
    "firstSeenAt": "2026-03-17T16:20:30.000Z",
    "lastSeenAt": "2026-03-23T07:20:14.767Z"
  },
  "University of the Aegean / EWC:cred:ewc:photo-id-sd-jwt:sd-jwt-vc": {
    "firstSeenAt": "2026-03-17T16:20:30.000Z",
    "lastSeenAt": "2026-03-23T07:20:14.767Z"
  },
  "University of the Aegean / EWC:cred:ewc:personal-contact-details-sd-jwt:sd-jwt-vc": {
    "firstSeenAt": "2026-03-17T16:20:30.000Z",
    "lastSeenAt": "2026-03-23T07:20:14.767Z"
  },
  "University of the Aegean / EWC:cred:ewc:loyalty-card-sd-jwt:sd-jwt-vc": {
    "firstSeenAt": "2026-03-17T16:20:30.000Z",
    "lastSeenAt": "2026-03-23T07:20:14.767Z"
  },
  "FIDES Community:cred:fides:organization-profile:sd-jwt-vc": {
    "firstSeenAt": "2026-03-12T00:00:00.000Z",
    "lastSeenAt": "2026-03-23T07:20:14.767Z"
  },
  "FIDES Community:cred:fides:criminal-record-check:sd-jwt-vc": {
    "firstSeenAt": "2026-03-12T00:00:00.000Z",
    "lastSeenAt": "2026-03-23T07:20:14.767Z"
  },
  "FIDES Community:cred:fides:verified-employee:sd-jwt-vc": {
    "firstSeenAt": "2026-03-12T00:00:00.000Z",
    "lastSeenAt": "2026-03-23T07:20:14.767Z"
  },
  "FIDES Community:cred:fides:higher-education-diploma:sd-jwt-vc": {
    "firstSeenAt": "2026-03-12T00:00:00.000Z",
    "lastSeenAt": "2026-03-23T07:20:14.767Z"
  },
  "FIDES Community:cred:fides:iso-certificate:sd-jwt-vc": {
    "firstSeenAt": "2026-03-12T00:00:00.000Z",
    "lastSeenAt": "2026-03-23T07:20:14.767Z"
  },
  "FIDES Community:cred:fides:upper-secondary-education:sd-jwt-vc": {
    "firstSeenAt": "2026-03-12T00:00:00.000Z",
    "lastSeenAt": "2026-03-23T07:20:14.767Z"
  },
  "European Commission:cred:eu:age-verification-mdoc:mdoc": {
    "firstSeenAt": "2026-03-18T12:12:34.000Z",
    "lastSeenAt": "2026-03-23T07:20:14.767Z"
  },
  "European Commission:cred:eu:mvrc-mdoc:mdoc": {
    "firstSeenAt": "2026-03-18T12:12:34.000Z",
    "lastSeenAt": "2026-03-23T07:20:14.767Z"
  },
  "European Commission:cred:eu:photoid-mdoc-iso23220:mdoc": {
    "firstSeenAt": "2026-03-18T12:12:34.000Z",
    "lastSeenAt": "2026-03-23T07:20:14.767Z"
  },
  "UN/CEFACT:cred:uncefact:dcc:vcdm-2-0": {
    "firstSeenAt": "2026-03-19T00:00:00.000Z",
    "lastSeenAt": "2026-03-23T07:20:14.767Z"
  },
  "UN/CEFACT:cred:uncefact:dpp:vcdm-2-0": {
    "firstSeenAt": "2026-03-19T00:00:00.000Z",
    "lastSeenAt": "2026-03-23T07:20:14.767Z"
  },
  "UN/CEFACT:cred:uncefact:dte:vcdm-2-0": {
    "firstSeenAt": "2026-03-19T00:00:00.000Z",
    "lastSeenAt": "2026-03-23T07:20:14.767Z"
  },
  "UN/CEFACT:cred:uncefact:dfr:vcdm-2-0": {
    "firstSeenAt": "2026-03-19T00:00:00.000Z",
    "lastSeenAt": "2026-03-23T07:20:14.767Z"
  },
  "UN/CEFACT:cred:uncefact:dia:vcdm-2-0": {
    "firstSeenAt": "2026-03-19T00:00:00.000Z",
    "lastSeenAt": "2026-03-23T07:20:14.767Z"
  },
  "UN/CEFACT:cred:uncefact:invoice:vcdm-2-0": {
    "firstSeenAt": "2026-03-19T00:00:00.000Z",
    "lastSeenAt": "2026-03-23T07:20:14.767Z"
  },
  "UN/CEFACT:cred:uncefact:packing-list:vcdm-2-0": {
    "firstSeenAt": "2026-03-19T00:00:00.000Z",
    "lastSeenAt": "2026-03-23T07:20:14.767Z"
  },
  "UN/CEFACT:cred:uncefact:bill-of-lading:vcdm-2-0": {
    "firstSeenAt": "2026-03-19T00:00:00.000Z",
    "lastSeenAt": "2026-03-23T07:20:14.767Z"
  },
  "UN/CEFACT:cred:uncefact:waybill:vcdm-2-0": {
    "firstSeenAt": "2026-03-19T00:00:00.000Z",
    "lastSeenAt": "2026-03-19T17:01:48.641Z"
  },
  "UN/CEFACT:cred:uncefact:certificate-of-origin:vcdm-2-0": {
    "firstSeenAt": "2026-03-19T00:00:00.000Z",
    "lastSeenAt": "2026-03-23T07:20:14.767Z"
  },
  "UN/CEFACT:cred:uncefact:insurance-certificate:vcdm-2-0": {
    "firstSeenAt": "2026-03-19T00:00:00.000Z",
    "lastSeenAt": "2026-03-23T07:20:14.767Z"
  },
  "UN/CEFACT:cred:uncefact:transport-instruction:vcdm-2-0": {
    "firstSeenAt": "2026-03-19T00:00:00.000Z",
    "lastSeenAt": "2026-03-19T17:01:48.641Z"
  },
  "UN/CEFACT:cred:uncefact:customs-declaration:vcdm-2-0": {
    "firstSeenAt": "2026-03-22T00:00:00.000Z",
    "lastSeenAt": "2026-03-23T07:20:14.767Z"
  },
  "UN/CEFACT:cred:uncefact:purchase-order:vcdm-2-0": {
    "firstSeenAt": "2026-03-22T00:00:00.000Z",
    "lastSeenAt": "2026-03-23T07:20:14.767Z"
  },
  "UN/CEFACT:cred:uncefact:warehouse-receipt:vcdm-2-0": {
    "firstSeenAt": "2026-03-22T00:00:00.000Z",
    "lastSeenAt": "2026-03-23T07:20:14.767Z"
  },
  "org:eu:cred:eu:diploma-vc-sd-jwt:sd-jwt-vc": {
    "firstSeenAt": "2026-03-19T15:39:51.000Z",
    "lastSeenAt": "2026-04-20T13:02:09.285Z"
  },
  "org:eu:cred:eu:ehic-sd-jwt-vc:sd-jwt-vc": {
    "firstSeenAt": "2026-03-19T15:39:51.000Z",
    "lastSeenAt": "2026-04-20T13:02:09.285Z"
  },
  "org:eu:cred:eu:hiid-sd-jwt-vc:sd-jwt-vc": {
    "firstSeenAt": "2026-03-19T15:39:51.000Z",
    "lastSeenAt": "2026-04-20T13:02:09.285Z"
  },
  "org:eu:cred:eu:iban-sd-jwt-vc:sd-jwt-vc": {
    "firstSeenAt": "2026-03-19T15:39:51.000Z",
    "lastSeenAt": "2026-04-20T13:02:09.285Z"
  },
  "org:eu:cred:eu:msisdn-sd-jwt-vc:sd-jwt-vc": {
    "firstSeenAt": "2026-03-19T15:39:51.000Z",
    "lastSeenAt": "2026-04-20T13:02:09.285Z"
  },
  "org:eu:cred:eu:pda1-sd-jwt-vc:sd-jwt-vc": {
    "firstSeenAt": "2026-03-19T15:39:51.000Z",
    "lastSeenAt": "2026-04-20T13:02:09.285Z"
  },
  "org:eu:cred:eu:pid-vc-sd-jwt:sd-jwt-vc": {
    "firstSeenAt": "2026-03-19T15:39:51.000Z",
    "lastSeenAt": "2026-04-20T13:02:09.285Z"
  },
  "org:eu:cred:eu:por-sd-jwt-vc:sd-jwt-vc": {
    "firstSeenAt": "2026-03-19T15:39:51.000Z",
    "lastSeenAt": "2026-04-20T13:02:09.285Z"
  },
  "org:eu:cred:eu:tax-residency-vc-sd-jwt:sd-jwt-vc": {
    "firstSeenAt": "2026-03-19T15:39:51.000Z",
    "lastSeenAt": "2026-04-20T13:02:09.285Z"
  },
  "org:eu:cred:eu:tax-sd-jwt-vc:sd-jwt-vc": {
    "firstSeenAt": "2026-03-19T15:39:51.000Z",
    "lastSeenAt": "2026-04-20T13:02:09.285Z"
  },
  "org:eu:cred:eu:cor-mdoc:mdoc": {
    "firstSeenAt": "2026-03-19T15:39:51.000Z",
    "lastSeenAt": "2026-04-20T13:02:09.285Z"
  },
  "org:eu:cred:eu:ehic-mdoc:mdoc": {
    "firstSeenAt": "2026-03-19T15:39:51.000Z",
    "lastSeenAt": "2026-04-20T13:02:09.285Z"
  },
  "org:eu:cred:eu:employee-mdoc:mdoc": {
    "firstSeenAt": "2026-03-19T15:39:51.000Z",
    "lastSeenAt": "2026-04-20T13:02:09.285Z"
  },
  "org:eu:cred:eu:hiid-mdoc:mdoc": {
    "firstSeenAt": "2026-03-19T15:39:51.000Z",
    "lastSeenAt": "2026-04-20T13:02:09.285Z"
  },
  "org:eu:cred:eu:iban-mdoc:mdoc": {
    "firstSeenAt": "2026-03-19T15:39:51.000Z",
    "lastSeenAt": "2026-04-20T13:02:09.285Z"
  },
  "org:eu:cred:eu:loyalty-mdoc:mdoc": {
    "firstSeenAt": "2026-03-19T15:39:51.000Z",
    "lastSeenAt": "2026-04-20T13:02:09.285Z"
  },
  "org:eu:cred:eu:mdl-mdoc:mdoc": {
    "firstSeenAt": "2026-03-19T15:39:51.000Z",
    "lastSeenAt": "2026-04-20T13:02:09.285Z"
  },
  "org:eu:cred:eu:msisdn-mdoc:mdoc": {
    "firstSeenAt": "2026-03-19T15:39:51.000Z",
    "lastSeenAt": "2026-04-20T13:02:09.285Z"
  },
  "org:eu:cred:eu:pda1-mdoc:mdoc": {
    "firstSeenAt": "2026-03-19T15:39:51.000Z",
    "lastSeenAt": "2026-04-20T13:02:09.285Z"
  },
  "org:eu:cred:eu:photoid-mdoc:mdoc": {
    "firstSeenAt": "2026-03-19T15:39:51.000Z",
    "lastSeenAt": "2026-04-20T13:02:09.285Z"
  },
  "org:eu:cred:eu:pid-mdoc:mdoc": {
    "firstSeenAt": "2026-03-19T15:39:51.000Z",
    "lastSeenAt": "2026-04-20T13:02:09.285Z"
  },
  "org:eu:cred:eu:pid-mdoc-deferred-mdoc:mdoc": {
    "firstSeenAt": "2026-03-19T15:39:51.000Z",
    "lastSeenAt": "2026-04-20T13:02:09.285Z"
  },
  "org:eu:cred:eu:por-mdoc:mdoc": {
    "firstSeenAt": "2026-03-19T15:39:51.000Z",
    "lastSeenAt": "2026-04-20T13:02:09.285Z"
  },
  "org:eu:cred:eu:seafarer-mdoc:mdoc": {
    "firstSeenAt": "2026-03-19T15:39:51.000Z",
    "lastSeenAt": "2026-04-20T13:02:09.285Z"
  },
  "org:eu:cred:eu:tax-mdoc:mdoc": {
    "firstSeenAt": "2026-03-19T15:39:51.000Z",
    "lastSeenAt": "2026-04-20T13:02:09.285Z"
  },
  "org:eu:cred:eu:reservation-mdoc:mdoc": {
    "firstSeenAt": "2026-03-19T15:39:51.000Z",
    "lastSeenAt": "2026-04-20T13:02:09.285Z"
  },
  "org:eu:cred:eu:age-verification-mdoc:mdoc": {
    "firstSeenAt": "2026-03-19T15:39:51.000Z",
    "lastSeenAt": "2026-04-20T13:02:09.285Z"
  },
  "org:eu:cred:eu:mvrc-mdoc:mdoc": {
    "firstSeenAt": "2026-03-19T15:39:51.000Z",
    "lastSeenAt": "2026-04-20T13:02:09.285Z"
  },
  "org:eu:cred:eu:photoid-mdoc-iso23220:mdoc": {
    "firstSeenAt": "2026-03-19T15:39:51.000Z",
    "lastSeenAt": "2026-04-20T13:02:09.285Z"
  },
  "org:ewc:cred:ewc:pda1-sd-jwt:sd-jwt-vc": {
    "firstSeenAt": "2026-03-19T15:39:51.000Z",
    "lastSeenAt": "2026-04-20T13:02:09.285Z"
  },
  "org:ewc:cred:ewc:pda2-sd-jwt:sd-jwt-vc": {
    "firstSeenAt": "2026-03-19T15:39:51.000Z",
    "lastSeenAt": "2026-04-20T13:02:09.285Z"
  },
  "org:ewc:cred:ewc:id-card-jwt-vc:jwt-vc": {
    "firstSeenAt": "2026-03-19T15:39:51.000Z",
    "lastSeenAt": "2026-04-20T13:02:09.285Z"
  },
  "org:ewc:cred:ewc:pid-sd-jwt:sd-jwt-vc": {
    "firstSeenAt": "2026-03-19T15:39:51.000Z",
    "lastSeenAt": "2026-04-20T13:02:09.285Z"
  },
  "org:ewc:cred:ewc:epassport-sd-jwt:sd-jwt-vc": {
    "firstSeenAt": "2026-03-19T15:39:51.000Z",
    "lastSeenAt": "2026-04-20T13:02:09.285Z"
  },
  "org:ewc:cred:ewc:student-id-sd-jwt:sd-jwt-vc": {
    "firstSeenAt": "2026-03-19T15:39:51.000Z",
    "lastSeenAt": "2026-04-20T13:02:09.285Z"
  },
  "org:ewc:cred:ewc:ferry-boarding-pass-sd-jwt:sd-jwt-vc": {
    "firstSeenAt": "2026-03-19T15:39:51.000Z",
    "lastSeenAt": "2026-04-20T13:02:09.285Z"
  },
  "org:ewc:cred:ewc:vreceipt-sd-jwt:sd-jwt-vc": {
    "firstSeenAt": "2026-03-19T15:39:51.000Z",
    "lastSeenAt": "2026-04-20T13:02:09.285Z"
  },
  "org:ewc:cred:ewc:pid-eudi-sd-jwt:sd-jwt-vc": {
    "firstSeenAt": "2026-03-19T15:39:51.000Z",
    "lastSeenAt": "2026-04-20T13:02:09.285Z"
  },
  "org:ewc:cred:ewc:pid-eudi-mdoc:mso-mdoc": {
    "firstSeenAt": "2026-03-19T15:39:51.000Z",
    "lastSeenAt": "2026-04-20T13:02:09.285Z"
  },
  "org:ewc:cred:ewc:payment-wallet-attestation-sd-jwt:sd-jwt-vc": {
    "firstSeenAt": "2026-03-19T15:39:51.000Z",
    "lastSeenAt": "2026-04-20T13:02:09.285Z"
  },
  "org:ewc:cred:ewc:photo-id-sd-jwt:sd-jwt-vc": {
    "firstSeenAt": "2026-03-19T15:39:51.000Z",
    "lastSeenAt": "2026-04-20T13:02:09.285Z"
  },
  "org:ewc:cred:ewc:personal-contact-details-sd-jwt:sd-jwt-vc": {
    "firstSeenAt": "2026-03-19T15:39:51.000Z",
    "lastSeenAt": "2026-04-20T13:02:09.285Z"
  },
  "org:ewc:cred:ewc:loyalty-card-sd-jwt:sd-jwt-vc": {
    "firstSeenAt": "2026-03-19T15:39:51.000Z",
    "lastSeenAt": "2026-04-20T13:02:09.285Z"
  },
  "org:fides:cred:fides:lpid:sd-jwt-vc": {
    "firstSeenAt": "2026-03-15T00:00:00.000Z",
    "lastSeenAt": "2026-04-20T13:02:09.285Z"
  },
  "org:fides:cred:fides:bri:sd-jwt-vc": {
    "firstSeenAt": "2026-03-15T00:00:00.000Z",
    "lastSeenAt": "2026-04-20T13:02:09.285Z"
  },
  "org:fides:cred:fides:brp:sd-jwt-vc": {
    "firstSeenAt": "2026-03-15T00:00:00.000Z",
    "lastSeenAt": "2026-04-20T13:02:09.285Z"
  },
  "org:fides:cred:fides:company-roles:sd-jwt-vc": {
    "firstSeenAt": "2026-03-15T00:00:00.000Z",
    "lastSeenAt": "2026-04-20T13:02:09.285Z"
  },
  "org:fides:cred:fides:contact-details:sd-jwt-vc": {
    "firstSeenAt": "2026-03-15T00:00:00.000Z",
    "lastSeenAt": "2026-04-20T13:02:09.285Z"
  },
  "org:fides:cred:fides:einvoicing:sd-jwt-vc": {
    "firstSeenAt": "2026-03-15T00:00:00.000Z",
    "lastSeenAt": "2026-04-20T13:02:09.285Z"
  },
  "org:fides:cred:fides:green-lane:sd-jwt-vc": {
    "firstSeenAt": "2026-03-15T00:00:00.000Z",
    "lastSeenAt": "2026-04-20T13:02:09.285Z"
  },
  "org:fides:cred:fides:iban:sd-jwt-vc": {
    "firstSeenAt": "2026-03-15T00:00:00.000Z",
    "lastSeenAt": "2026-04-20T13:02:09.285Z"
  },
  "org:fides:cred:fides:iscc-sd:sd-jwt-vc": {
    "firstSeenAt": "2026-03-15T00:00:00.000Z",
    "lastSeenAt": "2026-04-20T13:02:09.285Z"
  },
  "org:fides:cred:fides:iscc-cert:sd-jwt-vc": {
    "firstSeenAt": "2026-03-15T00:00:00.000Z",
    "lastSeenAt": "2026-04-20T13:02:09.285Z"
  },
  "org:fides:cred:fides:iscc-role:sd-jwt-vc": {
    "firstSeenAt": "2026-03-15T00:00:00.000Z",
    "lastSeenAt": "2026-04-20T13:02:09.285Z"
  },
  "org:fides:cred:fides:iscc-cb:sd-jwt-vc": {
    "firstSeenAt": "2026-03-15T00:00:00.000Z",
    "lastSeenAt": "2026-04-20T13:02:09.285Z"
  },
  "org:fides:cred:fides:iscc-rev-user:sd-jwt-vc": {
    "firstSeenAt": "2026-03-15T00:00:00.000Z",
    "lastSeenAt": "2026-04-20T13:02:09.285Z"
  },
  "org:fides:cred:fides:notary-incorporation:sd-jwt-vc": {
    "firstSeenAt": "2026-03-15T00:00:00.000Z",
    "lastSeenAt": "2026-04-20T13:02:09.285Z"
  },
  "org:fides:cred:fides:pid:sd-jwt-vc": {
    "firstSeenAt": "2026-03-15T00:00:00.000Z",
    "lastSeenAt": "2026-04-20T13:02:09.285Z"
  },
  "org:fides:cred:fides:vat:sd-jwt-vc": {
    "firstSeenAt": "2026-03-15T00:00:00.000Z",
    "lastSeenAt": "2026-04-20T13:02:09.285Z"
  },
  "org:fides:cred:fides:organization-profile:sd-jwt-vc": {
    "firstSeenAt": "2026-03-15T00:00:00.000Z",
    "lastSeenAt": "2026-04-20T13:02:09.285Z"
  },
  "org:fides:cred:fides:criminal-record-check:sd-jwt-vc": {
    "firstSeenAt": "2026-03-15T00:00:00.000Z",
    "lastSeenAt": "2026-04-20T13:02:09.285Z"
  },
  "org:fides:cred:fides:verified-employee:sd-jwt-vc": {
    "firstSeenAt": "2026-03-15T00:00:00.000Z",
    "lastSeenAt": "2026-04-20T13:02:09.285Z"
  },
  "org:fides:cred:fides:higher-education-diploma:sd-jwt-vc": {
    "firstSeenAt": "2026-03-15T00:00:00.000Z",
    "lastSeenAt": "2026-04-20T13:02:09.285Z"
  },
  "org:fides:cred:fides:iso-certificate:sd-jwt-vc": {
    "firstSeenAt": "2026-03-15T00:00:00.000Z",
    "lastSeenAt": "2026-04-20T13:02:09.285Z"
  },
  "org:fides:cred:fides:upper-secondary-education:sd-jwt-vc": {
    "firstSeenAt": "2026-03-15T00:00:00.000Z",
    "lastSeenAt": "2026-04-20T13:02:09.285Z"
  },
  "org:uncefact:cred:uncefact:dcc:vcdm-2-0": {
    "firstSeenAt": "2026-03-22T00:00:00.000Z",
    "lastSeenAt": "2026-04-20T13:02:09.285Z"
  },
  "org:uncefact:cred:uncefact:dpp:vcdm-2-0": {
    "firstSeenAt": "2026-03-22T00:00:00.000Z",
    "lastSeenAt": "2026-04-20T13:02:09.285Z"
  },
  "org:uncefact:cred:uncefact:dte:vcdm-2-0": {
    "firstSeenAt": "2026-03-22T00:00:00.000Z",
    "lastSeenAt": "2026-04-20T13:02:09.285Z"
  },
  "org:uncefact:cred:uncefact:dfr:vcdm-2-0": {
    "firstSeenAt": "2026-03-22T00:00:00.000Z",
    "lastSeenAt": "2026-04-20T13:02:09.285Z"
  },
  "org:uncefact:cred:uncefact:dia:vcdm-2-0": {
    "firstSeenAt": "2026-03-22T00:00:00.000Z",
    "lastSeenAt": "2026-04-20T13:02:09.285Z"
  },
  "org:uncefact:cred:uncefact:invoice:vcdm-2-0": {
    "firstSeenAt": "2026-03-22T00:00:00.000Z",
    "lastSeenAt": "2026-04-20T13:02:09.285Z"
  },
  "org:uncefact:cred:uncefact:bill-of-lading:vcdm-2-0": {
    "firstSeenAt": "2026-03-22T00:00:00.000Z",
    "lastSeenAt": "2026-04-20T13:02:09.285Z"
  },
  "org:uncefact:cred:uncefact:certificate-of-origin:vcdm-2-0": {
    "firstSeenAt": "2026-03-22T00:00:00.000Z",
    "lastSeenAt": "2026-04-20T13:02:09.285Z"
  },
  "org:uncefact:cred:uncefact:customs-declaration:vcdm-2-0": {
    "firstSeenAt": "2026-03-22T00:00:00.000Z",
    "lastSeenAt": "2026-04-20T13:02:09.285Z"
  },
  "org:uncefact:cred:uncefact:insurance-certificate:vcdm-2-0": {
    "firstSeenAt": "2026-03-22T00:00:00.000Z",
    "lastSeenAt": "2026-04-20T13:02:09.285Z"
  },
  "org:uncefact:cred:uncefact:packing-list:vcdm-2-0": {
    "firstSeenAt": "2026-03-22T00:00:00.000Z",
    "lastSeenAt": "2026-04-20T13:02:09.285Z"
  },
  "org:uncefact:cred:uncefact:purchase-order:vcdm-2-0": {
    "firstSeenAt": "2026-03-22T00:00:00.000Z",
    "lastSeenAt": "2026-04-20T13:02:09.285Z"
  },
  "org:uncefact:cred:uncefact:warehouse-receipt:vcdm-2-0": {
    "firstSeenAt": "2026-03-22T00:00:00.000Z",
    "lastSeenAt": "2026-04-20T13:02:09.285Z"
  },
  "org:fides:cred:fides:verifiable-bank-statement:sd-jwt-vc": {
    "firstSeenAt": "2026-04-02T00:00:00.000Z",
    "lastSeenAt": "2026-04-20T13:02:09.285Z"
  },
  "org:fides:cred:fides:verifiable-payment:sd-jwt-vc": {
    "firstSeenAt": "2026-04-02T00:00:00.000Z",
    "lastSeenAt": "2026-04-20T13:02:09.285Z"
  },
  "org:fides:cred:fides:verifiable-payment-receipt:sd-jwt-vc": {
    "firstSeenAt": "2026-04-02T00:00:00.000Z",
    "lastSeenAt": "2026-04-20T13:02:09.285Z"
  },
  "org:swiyu:cred:swiyu:betaid-sdjwt:sd-jwt-vc": {
    "firstSeenAt": "2026-04-02T19:01:41.000Z",
    "lastSeenAt": "2026-04-20T13:02:09.285Z"
  },
  "org:gaia-x:cred:gaiax:legal-participant:vcdm-1-1": {
    "firstSeenAt": "2026-04-09T12:00:00.000Z",
    "lastSeenAt": "2026-04-20T13:02:09.285Z"
  },
  "org:gaia-x:cred:gaiax:legal-registration-number:vcdm-1-1": {
    "firstSeenAt": "2026-04-09T12:00:00.000Z",
    "lastSeenAt": "2026-04-20T13:02:09.285Z"
  },
  "org:gaia-x:cred:gaiax:terms-and-conditions:vcdm-1-1": {
    "firstSeenAt": "2026-04-09T12:00:00.000Z",
    "lastSeenAt": "2026-04-20T13:02:09.285Z"
  },
  "org:gaia-x:cred:gaiax:resource:vcdm-1-1": {
    "firstSeenAt": "2026-04-09T12:00:00.000Z",
    "lastSeenAt": "2026-04-20T13:02:09.285Z"
  },
  "org:gaia-x:cred:gaiax:service-offering:vcdm-1-1": {
    "firstSeenAt": "2026-04-09T12:00:00.000Z",
    "lastSeenAt": "2026-04-20T13:02:09.285Z"
  },
  "org:gaia-x:cred:gaiax:data-resource:vcdm-1-1": {
    "firstSeenAt": "2026-04-09T12:00:00.000Z",
    "lastSeenAt": "2026-04-20T13:02:09.285Z"
  },
  "org:gaia-x:cred:gaiax:physical-resource:vcdm-1-1": {
    "firstSeenAt": "2026-04-09T12:00:00.000Z",
    "lastSeenAt": "2026-04-20T13:02:09.285Z"
  },
  "org:gaia-x:cred:gaiax:software-resource:vcdm-1-1": {
    "firstSeenAt": "2026-04-09T12:00:00.000Z",
    "lastSeenAt": "2026-04-20T13:02:09.285Z"
  },
  "org:gaia-x:cred:gaiax:compliance-credential:vcdm-1-1": {
    "firstSeenAt": "2026-04-09T12:00:00.000Z",
    "lastSeenAt": "2026-04-20T13:02:09.285Z"
  }
}